README.md
setup.py
cifl_target_gsheets/__init__.py
cifl_target_gsheets.egg-info/PKG-INFO
cifl_target_gsheets.egg-info/SOURCES.txt
cifl_target_gsheets.egg-info/dependency_links.txt
cifl_target_gsheets.egg-info/entry_points.txt
cifl_target_gsheets.egg-info/not-zip-safe
cifl_target_gsheets.egg-info/requires.txt
cifl_target_gsheets.egg-info/top_level.txt