Metadata-Version: 1.0
Name: cifl-target-gsheets
Version: 0.1.0
Summary: Singer.oi CIFL Target for Google Sheets
Home-page: UNKNOWN
Author: CIFL
Author-email: UNKNOWN
License: MIT
Platform: UNKNOWN
